README.md
pyproject.toml
src/__init__.py
src/eurodb.py
src/eurodb.egg-info/PKG-INFO
src/eurodb.egg-info/SOURCES.txt
src/eurodb.egg-info/dependency_links.txt
src/eurodb.egg-info/top_level.txt