Metadata-Version: 2.1
Name: eurodb
Version: 1.0.0
Summary: A simple PYODBC/SQLAlchemy wrapper for connection handling
Author-email: Ratouney - Maxime de la Fouchardière <maxime.de-la-fouchardiere@eurodw.eu>
Classifier: Development Status :: 3 - Alpha
Classifier: Programming Language :: Python :: 3
Classifier: License :: Other/Proprietary License
Classifier: Operating System :: OS Independent
Requires-Python: >=3.7
